cells2table/__init__.py
cells2table/docling.py
cells2table/models/PaddlePaddle/__init__.py
cells2table/models/PaddlePaddle/cell_detection.py
cells2table/models/PaddlePaddle/pipeline.py
cells2table/models/PaddlePaddle/table_classification.py
cells2table/models/__init__.py
cells2table/models/utils/download.py
cells2table/models/utils/runtimes/__init__.py
cells2table/models/utils/runtimes/onnx.py
cells2table/models/utils/tasks/__init__.py
cells2table/models/utils/tasks/base.py
cells2table/models/utils/tasks/classification.py
cells2table/models/utils/tasks/detection.py
cells2table/py.typed
cells2table/utils/__init__.py
cells2table/utils/table.py
cells2table/utils/visualize.py
cells2table-0.2.1.dist-info/licenses/LICENSE
cells2table-0.2.1.dist-info/WHEEL
cells2table-0.2.1.dist-info/entry_points.txt
cells2table-0.2.1.dist-info/METADATA
cells2table-0.2.1.dist-info/RECORD
