Metadata-Version: 2.4
Name: cells2table
Version: 0.2.1
Summary: Table image parsing with cell detection models
Keywords: docling,plugin
Author: jspast
Author-email: jspast <140563347+jspast@users.noreply.github.com>
License-Expression: MIT
License-File: LICENSE
Classifier: Operating System :: OS Independent
Classifier: Programming Language :: Python :: 3
Requires-Dist: huggingface-hub>=0.36.0
Requires-Dist: numpy>=2.2.0
Requires-Dist: opencv-python>=4.11.0.86
Requires-Dist: onnxruntime>=1.23.2 ; extra == 'cpu'
Requires-Dist: onnxruntime-gpu>=1.23.2 ; extra == 'cuda'
Requires-Dist: docling>=2.66.0 ; extra == 'docling'
Requires-Dist: onnxruntime-openvino>=1.23.0 ; extra == 'openvino'
Requires-Python: >=3.12
Project-URL: Homepage, https://github.com/jspast/cells2table
Project-URL: Issues, https://github.com/jspast/cells2table/issues
Provides-Extra: cpu
Provides-Extra: cuda
Provides-Extra: docling
Provides-Extra: openvino
